subpipe/__init__.py
subpipe-0.0.6.dist-info/METADATA
subpipe-0.0.6.dist-info/WHEEL
subpipe-0.0.6.dist-info/RECORD
